Workbook

Sheet Hypothèses
A1: HYPOTHÈSES DE CALCUL — IMPORTATION DE MACHINES AGRICOLES ZENO (CHINE) → NIAMEY
A2: Cellules en BLEU = à saisir / à ajuster. Cellules en NOIR = calculées. Fond jaune = hypothèse à confirmer.
A4: 1. CHANGE
A5: Taux de change 1 USD = | B5: 560 | C5: Moyenne 2026 : 559 XOF/USD (exchange-rates.org). 560 retenu par prudence.
A7: 2. EMBALLAGE (caisses bois export)
A8: Coefficient de majoration du volume | B8: 1.15 | C8: Caisse bois : +15 % sur le volume machine.
A9: Coefficient de majoration du poids | B9: 1.12 | C9: Caisse bois : +12 % sur le poids machine.
A11: 3. LOGISTIQUE — 1 conteneur 20' (Qingdao → Lomé → Niamey)
A12: Fret maritime Qingdao → Lomé, 20' FCL (USD) | B12: 1900 | C12: Marché 2026 Chine → Lomé : 1 350 à 1 950 USD port à port, surcharges incluses.
A13: Fret maritime (FCFA) | B13: ='Hypothèses'!B12*'Hypothèses'!B5 | C13: Fret en dollars × taux de change
A14: Assurance transport (% de FOB + fret) | B14: 0.005 | C14: Police ad valorem usuelle : 0,4 à 0,7 %.
A15: Frais portuaires Lomé, THC, transit maritime | B15: 450000 | C15: À confirmer par le transitaire.
A16: Transport routier Lomé → Niamey (conteneur 20') | B16: 1600000 | C16: Corridor Lomé : ~1 300 000 F/20' vers Ouagadougou ; majoré pour Niamey (~1 250 km).
A17: Transit, dédouanement et manutention à Niamey | B17: 350000 | C17: Honoraires transitaire + frais de dossier.
A18: Inspection avant embarquement (% du FOB) | B18: 0.01 | C18: Programme de vérification des importations (COTECNA).
A19: Frais bancaires et transfert international (% du FOB) | B19: 0.015 | C19: Ouverture de dossier, commissions, 50 % d'acompte TT.
A20: Stockage et manutention magasin Niamey | B20: 200000 | C20: Déchargement, mise en magasin, calage.
A21: Provision SAV et garantie 1 an (% du revient) | B21: 0.02 | C21: Pièces d'usure et interventions sous garantie.
A23: 4. DROITS ET TAXES À L'IMPORT — NIGER (TEC UEMOA/CEDEAO), base CAF
A24: Droit de douane (DD) — catégorie 1, biens d'équipement | B24: 0.05 | C24: Machines agricoles SH 8433/8436/8479 : catégorie 1 = 5 %. À FAIRE CONFIRMER par le transitaire.
A25: Redevance statistique (RS) | B25: 0.01
A26: Prélèvement communautaire de solidarité (PCS-UEMOA) | B26: 0.01
A27: Prélèvement communautaire (PC-CEDEAO) | B27: 0.005
A28: TVA à l'import (récupérable) | B28: 0.19 | C28: Taux de droit commun au Niger. Récupérable : hors prix de revient.
A29: Acompte ISB/AIB (imputable) | B29: 0.02 | C29: Imputable sur l'impôt sur les bénéfices : hors prix de revient.
A31: 5. POLITIQUE DE PRIX (coefficient appliqué au prix de revient)
A32: Scénario PRUDENT | B32: 1.45 | C32: Prix d'attaque / marchés à forte concurrence.
A33: Scénario CONSEILLÉ | B33: 1.7 | C33: Positionnement de référence, cohérent avec le marché ouest-africain.
A34: Scénario PREMIUM | B34: 1.9 | C34: Vente à l'unité, avec installation, formation et SAV.
A35: Arrondi commercial des prix de vente (FCFA) | B35: 5000 | C35: Les prix de vente sont arrondis à ce multiple.
A37: SOURCES ET AVERTISSEMENTS
A38: • Prix fournisseur : cotation ZHENGZHOU ZENO MACHINERY CO., LTD du 19 août 2026, FOB Qingdao, MOQ 10 unités par modèle.
A39: • Délai fournisseur : 15 jours après paiement. Paiement : 50 % d'acompte TT, solde avant expédition. Garantie machine : 1 an.
A40: • Les coûts logistiques et les droits sont des ESTIMATIONS : faire confirmer par le transitaire et le bureau de douane avant engagement.
A41: • La TVA et l'acompte ISB sont récupérables/imputables : ils ne figurent pas dans le prix de revient mais pèsent sur la trésorerie.
A42: • Les prix de marché servant de repère proviennent de distributeurs ouest-africains ; à confirmer par un relevé sur le marché de Niamey.

Sheet Prix de revient
A1: PRIX DE REVIENT RENDU NIAMEY — DÉDOUANÉ, EN MAGASIN
A2: Fret, transport routier, frais portuaires et stockage répartis au PRORATA DU VOLUME ; assurance, inspection et frais bancaires au PRORATA DE LA VALEUR.
A4: N° | B4: Désignation | C4: Modèle | D4: Qté | E4: PU FOB (USD) | F4: FOB total (USD) | G4: FOB total (FCFA) | H4: Poids unit. (kg) | I4: Long. (m) | J4: Larg. (m) | K4: Haut. (m) | L4: Volume unit. emballé (m³) | M4: Volume total (m³) | N4: Poids total emballé (kg) | O4: Part volume | P4: Part valeur | Q4: Fret + route réparti (FCFA) | R4: Assurance (FCFA) | S4: VALEUR CAF (FCFA) | T4: DD 5 % (FCFA) | U4: RS+PCS+PC (FCFA) | V4: Total droits (FCFA) | W4: Autres frais logist. (FCFA) | X4: Sous-total (FCFA) | Y4: Provision SAV (FCFA) | Z4: REVIENT TOTAL (FCFA) | AA4: REVIENT UNIT. (FCFA) | AB4: TVA récup. (FCFA) | AC4: ISB imput. (FCFA)
A5: 1 | B5: Batteuse multifonction à céréales (riz, mil, sorgho, blé) — moteur diesel 6 CV, 400–600 kg/h, sur roues | C5: ZNST400 | D5: 10 | E5: 435 | F5: =D5*E5 | G5: =F5*'Hypothèses'!$B$5 | H5: 120 | I5: 1.2 | J5: 0.8 | K5: 1.1 | L5: =I5*J5*K5*'Hypothèses'!$B$8 | M5: =D5*L5 | N5: =D5*H5*'Hypothèses'!$B$9 | O5: =M5/$M$9 | P5: =G5/$G$9 | Q5: =('Hypothèses'!$B$13+'Hypothèses'!$B$16)*O5 | R5: ='Hypothèses'!$B$14*($G$9+'Hypothèses'!$B$13)*P5 | S5: =G5+Q5+R5 | T5: =S5*'Hypothèses'!$B$24 | U5: =S5*('Hypothèses'!$B$25+'Hypothèses'!$B$26+'Hypothèses'!$B$27) | V5: =T5+U5 | W5: =('Hypothèses'!$B$15+'Hypothèses'!$B$17+'Hypothèses'!$B$20)*O5+('Hypothèses'!$B$18+'Hypothèses'!$B$19)*$G$9*P5 | X5: =S5+V5+W5 | Y5: =X5*'Hypothèses'!$B$21 | Z5: =X5+Y5 | AA5: =Z5/D5 | AB5: =(S5+V5)*'Hypothèses'!$B$28 | AC5: =(S5+V5)*'Hypothèses'!$B$29
A6: 2 | B6: Décortiqueuse d'arachide manuelle — 40–80 kg/h | C6: ZNPS-1 | D6: 10 | E6: 87 | F6: =D6*E6 | G6: =F6*'Hypothèses'!$B$5 | H6: 25 | I6: 0.68 | J6: 0.35 | K6: 1.15 | L6: =I6*J6*K6*'Hypothèses'!$B$8 | M6: =D6*L6 | N6: =D6*H6*'Hypothèses'!$B$9 | O6: =M6/$M$9 | P6: =G6/$G$9 | Q6: =('Hypothèses'!$B$13+'Hypothèses'!$B$16)*O6 | R6: ='Hypothèses'!$B$14*($G$9+'Hypothèses'!$B$13)*P6 | S6: =G6+Q6+R6 | T6: =S6*'Hypothèses'!$B$24 | U6: =S6*('Hypothèses'!$B$25+'Hypothèses'!$B$26+'Hypothèses'!$B$27) | V6: =T6+U6 | W6: =('Hypothèses'!$B$15+'Hypothèses'!$B$17+'Hypothèses'!$B$20)*O6+('Hypothèses'!$B$18+'Hypothèses'!$B$19)*$G$9*P6 | X6: =S6+V6+W6 | Y6: =X6*'Hypothèses'!$B$21 | Z6: =X6+Y6 | AA6: =Z6/D6 | AB6: =(S6+V6)*'Hypothèses'!$B$28 | AC6: =(S6+V6)*'Hypothèses'!$B$29
A7: 3 | B7: Broyeur / moulin à céréales et résidus végétaux — moteur diesel 10 CV, cyclone, 200–400 kg/h | C7: ZNGQ360 | D7: 10 | E7: 582 | F7: =D7*E7 | G7: =F7*'Hypothèses'!$B$5 | H7: 260 | I7: 0.65 | J7: 0.6 | K7: 1.3 | L7: =I7*J7*K7*'Hypothèses'!$B$8 | M7: =D7*L7 | N7: =D7*H7*'Hypothèses'!$B$9 | O7: =M7/$M$9 | P7: =G7/$G$9 | Q7: =('Hypothèses'!$B$13+'Hypothèses'!$B$16)*O7 | R7: ='Hypothèses'!$B$14*($G$9+'Hypothèses'!$B$13)*P7 | S7: =G7+Q7+R7 | T7: =S7*'Hypothèses'!$B$24 | U7: =S7*('Hypothèses'!$B$25+'Hypothèses'!$B$26+'Hypothèses'!$B$27) | V7: =T7+U7 | W7: =('Hypothèses'!$B$15+'Hypothèses'!$B$17+'Hypothèses'!$B$20)*O7+('Hypothèses'!$B$18+'Hypothèses'!$B$19)*$G$9*P7 | X7: =S7+V7+W7 | Y7: =X7*'Hypothèses'!$B$21 | Z7: =X7+Y7 | AA7: =Z7/D7 | AB7: =(S7+V7)*'Hypothèses'!$B$28 | AC7: =(S7+V7)*'Hypothèses'!$B$29
A8: 4 | B8: Presse à huile motorisée inox (arachide, sésame, soja, tournesol) — électrique 4 kW, 10–30 kg/h | C8: ZYSS20 | D8: 10 | E8: 1035 | F8: =D8*E8 | G8: =F8*'Hypothèses'!$B$5 | H8: 60 | I8: 0.82 | J8: 0.45 | K8: 1 | L8: =I8*J8*K8*'Hypothèses'!$B$8 | M8: =D8*L8 | N8: =D8*H8*'Hypothèses'!$B$9 | O8: =M8/$M$9 | P8: =G8/$G$9 | Q8: =('Hypothèses'!$B$13+'Hypothèses'!$B$16)*O8 | R8: ='Hypothèses'!$B$14*($G$9+'Hypothèses'!$B$13)*P8 | S8: =G8+Q8+R8 | T8: =S8*'Hypothèses'!$B$24 | U8: =S8*('Hypothèses'!$B$25+'Hypothèses'!$B$26+'Hypothèses'!$B$27) | V8: =T8+U8 | W8: =('Hypothèses'!$B$15+'Hypothèses'!$B$17+'Hypothèses'!$B$20)*O8+('Hypothèses'!$B$18+'Hypothèses'!$B$19)*$G$9*P8 | X8: =S8+V8+W8 | Y8: =X8*'Hypothèses'!$B$21 | Z8: =X8+Y8 | AA8: =Z8/D8 | AB8: =(S8+V8)*'Hypothèses'!$B$28 | AC8: =(S8+V8)*'Hypothèses'!$B$29
B9: TOTAL / CONTENEUR 20' | D9: =SUM(D5:D8) | F9: =SUM(F5:F8) | G9: =SUM(G5:G8) | M9: =SUM(M5:M8) | N9: =SUM(N5:N8) | O9: =SUM(O5:O8) | P9: =SUM(P5:P8) | Q9: =SUM(Q5:Q8) | R9: =SUM(R5:R8) | S9: =SUM(S5:S8) | T9: =SUM(T5:T8) | ... Z9: =SUM(Z5:Z8) | AB9: =SUM(AB5:AB8) | AC9: =SUM(AC5:AC8)
B11: LÉGENDE
B12: • Bleu = donnée saisie (quantité, prix FOB, poids, dimensions du fournisseur). Noir = calcul automatique.
B13: • VALEUR CAF = FOB + fret maritime + transport routier jusqu'à la frontière + assurance : c'est la base de taxation en douane.
B14: • PRIX DE REVIENT = CAF + droits et taxes non récupérables + frais logistiques locaux + provision SAV.
B15: • TVA et acompte ISB ne sont PAS dans le prix de revient (récupérables), mais doivent être financés à l'enlèvement.

Sheet Prix de vente
A1: PRIX DE VENTE ESTIMATIFS — MARCHÉ NIGÉRIEN
A2: Prix arrondis au multiple défini en Hypothèses. Le repère de marché est indicatif : à confirmer par un relevé de prix à Niamey.
A4: N° | B4: Désignation | C4: Modèle | D4: Qté | E4: Prix de revient unitaire (FCFA) | F4: PV HT PRUDENT (FCFA) | G4: PV HT CONSEILLÉ (FCFA) | H4: PV HT PREMIUM (FCFA) | I4: PV TTC conseillé (FCFA) | J4: Marge unitaire conseillée (FCFA) | K4: Taux de marge / PV HT | L4: Repère marché Afr. Ouest (FCFA) | M4: Position vs marché | N4: CA HT conseillé sur 10 unités | O4: Marge brute sur 10 unités
A5: 1 | B5: Batteuse multifonction à céréales — diesel 6 CV | C5: ='Prix de revient'!C5 | D5: ='Prix de revient'!D5 | E5: ='Prix de revient'!AA5 | F5: =ROUND(E5*'Hypothèses'!$B$32/'Hypothèses'!$B$35,0)*'Hypothèses'!$B$35 | G5: =ROUND(E5*'Hypothèses'!$B$33/'Hypothèses'!$B$35,0)*'Hypothèses'!$B$35 | H5: =ROUND(E5*'Hypothèses'!$B$34/'Hypothèses'!$B$35,0)*'Hypothèses'!$B$35 | I5: =G5*(1+'Hypothèses'!$B$28) | J5: =G5-E5 | K5: =IF(G5=0,0,(G5-E5)/G5) | L5: 950000 | M5: =IF(L5=0,0,G5/L5-1) | N5: =D5*G5 | O5: =D5*(G5-E5)
A6: 2 | B6: Décortiqueuse d'arachide manuelle | C6: ='Prix de revient'!C6 | D6: ='Prix de revient'!D6 | E6: ='Prix de revient'!AA6 | F6: =ROUND(E6*'Hypothèses'!$B$32/'Hypothèses'!$B$35,0)*'Hypothèses'!$B$35 | G6: =ROUND(E6*'Hypothèses'!$B$33/'Hypothèses'!$B$35,0)*'Hypothèses'!$B$35 | H6: =ROUND(E6*'Hypothèses'!$B$34/'Hypothèses'!$B$35,0)*'Hypothèses'!$B$35 | I6: =G6*(1+'Hypothèses'!$B$28) | J6: =G6-E6 | K6: =IF(G6=0,0,(G6-E6)/G6) | L6: 200000 | M6: =IF(L6=0,0,G6/L6-1) | N6: =D6*G6 | O6: =D6*(G6-E6)
A7: 3 | B7: Broyeur / moulin à céréales — diesel 10 CV | C7: ='Prix de revient'!C7 | D7: ='Prix de revient'!D7 | E7: ='Prix de revient'!AA7 | F7: =ROUND(E7*'Hypothèses'!$B$32/'Hypothèses'!$B$35,0)*'Hypothèses'!$B$35 | G7: =ROUND(E7*'Hypothèses'!$B$33/'Hypothèses'!$B$35,0)*'Hypothèses'!$B$35 | H7: =ROUND(E7*'Hypothèses'!$B$34/'Hypothèses'!$B$35,0)*'Hypothèses'!$B$35 | I7: =G7*(1+'Hypothèses'!$B$28) | J7: =G7-E7 | K7: =IF(G7=0,0,(G7-E7)/G7) | L7: 850000 | M7: =IF(L7=0,0,G7/L7-1) | N7: =D7*G7 | O7: =D7*(G7-E7)
A8: 4 | B8: Presse à huile motorisée inox — 4 kW | C8: ='Prix de revient'!C8 | D8: ='Prix de revient'!D8 | E8: ='Prix de revient'!AA8 | F8: =ROUND(E8*'Hypothèses'!$B$32/'Hypothèses'!$B$35,0)*'Hypothèses'!$B$35 | G8: =ROUND(E8*'Hypothèses'!$B$33/'Hypothèses'!$B$35,0)*'Hypothèses'!$B$35 | H8: =ROUND(E8*'Hypothèses'!$B$34/'Hypothèses'!$B$35,0)*'Hypothèses'!$B$35 | I8: =G8*(1+'Hypothèses'!$B$28) | J8: =G8-E8 | K8: =IF(G8=0,0,(G8-E8)/G8) | L8: 1300000 | M8: =IF(L8=0,0,G8/L8-1) | N8: =D8*G8 | O8: =D8*(G8-E8)
B9: TOTAL | D9: =SUM(D5:D8) | K9: =IF(N9=0,0,O9/N9) | N9: =SUM(N5:N8) | O9: =SUM(O5:O8)
B11: LECTURE
B12: • PV HT PRUDENT : prix d'attaque pour un appel d'offres ou une vente en lot.
B13: • PV HT CONSEILLÉ : prix de référence catalogue, cohérent avec les prix pratiqués en Afrique de l'Ouest.
B14: • PV HT PREMIUM : vente à l'unité avec livraison, mise en service, formation et SAV.
B15: • Position vs marché : écart du prix conseillé par rapport au repère de marché (négatif = moins cher que le marché).
B16: • Repère marché (jaune) : à mettre à jour après relevé des prix pratiqués à Niamey.

Sheet Synthèse
A1: SYNTHÈSE DE L'OPÉRATION — 1 CONTENEUR 20' / 40 MACHINES
A3: A. DÉCAISSEMENTS
A4: Achat marchandise FOB Qingdao | B4: ='Prix de revient'!G9 | C4: 50 % d'acompte à la commande, solde avant expédition.
A5: Fret, assurance, transport et frais logistiques | B5: ='Prix de revient'!Q9+'Prix de revient'!R9+'Prix de revient'!W9
A6: Droits et taxes de douane (non récupérables) | B6: ='Prix de revient'!V9 | C6: DD + RS + PCS + PC sur la valeur CAF.
A7: Provision SAV et garantie | B7: ='Prix de revient'!Y9
A8: PRIX DE REVIENT TOTAL HT (rendu magasin Niamey) | B8: ='Prix de revient'!Z9 | C8: Base de calcul des prix de vente.
A9: TVA à l'import (récupérable) | B9: ='Prix de revient'!AB9 | C9: Récupérée sur la TVA collectée à la vente.
A10: Acompte ISB 2 % (imputable) | B10: ='Prix de revient'!AC9 | C10: Imputable sur l'impôt sur les bénéfices.
A11: TRÉSORERIE À MOBILISER (toutes taxes comprises) | B11: =B8+B9+B10 | C11: Montant réellement à financer jusqu'à la revente.
A13: B. CHIFFRE D'AFFAIRES ET MARGE (40 machines vendues)
A14: Chiffre d'affaires HT — scénario PRUDENT | B14: =SUMPRODUCT('Prix de vente'!D5:D8,'Prix de vente'!F5:F8)
A15: Chiffre d'affaires HT — scénario CONSEILLÉ | B15: =SUMPRODUCT('Prix de vente'!D5:D8,'Prix de vente'!G5:G8)
A16: Chiffre d'affaires HT — scénario PREMIUM | B16: =SUMPRODUCT('Prix de vente'!D5:D8,'Prix de vente'!H5:H8)
A17: Marge brute — scénario PRUDENT | B17: =B14-B8
A18: Marge brute — scénario CONSEILLÉ | B18: =B15-B8
A19: Marge brute — scénario PREMIUM | B19: =B16-B8
A20: Taux de marge sur CA — scénario CONSEILLÉ | B20: =IF(B15=0,0,B18/B15)
A21: Rentabilité de l'investissement — scénario CONSEILLÉ | B21: =IF(B8=0,0,B18/B8) | C21: Marge brute rapportée au prix de revient engagé.
A23: C. LOGISTIQUE DE L'OPÉRATION
A24: Volume total emballé | B24: ='Prix de revient'!M9 | C24: Conteneur 20' : ~33 m³ — chargement possible.
A25: Poids total emballé (kg) | B25: ='Prix de revient'!N9 | C25: Conteneur 20' : 28 t de charge utile.
A26: Nombre de machines | B26: ='Prix de revient'!D9 | C26: 4 modèles × 10 unités (MOQ du fournisseur).
A28: D. DÉLAI PRÉVISIONNEL
A29: Fabrication après paiement de l'acompte | B29: 15 jours
A30: Transport maritime Qingdao → Lomé | B30: 40 à 45 jours
A31: Déchargement, transit et route Lomé → Niamey | B31: 12 à 18 jours
A32: Dédouanement et mise en magasin à Niamey | B32: 5 à 8 jours
A33: DÉLAI TOTAL ESTIMÉ | B33: environ 75 à 90 jours
A35: E. POINTS À VÉRIFIER AVANT ENGAGEMENT
A36: • Classement tarifaire exact (SH) de chaque machine et catégorie du TEC : confirmer le taux de 5 % auprès du transitaire.
A37: • Existence d'une exonération ou d'un régime de faveur pour le matériel agricole (Code des investissements, projets financés).
A38: • Cotation ferme du transitaire : fret maritime, frais portuaires de Lomé, transport routier, transit et dédouanement.
A39: • Coût réel du transfert bancaire et disponibilité des devises pour l'acompte de 50 %.
A40: • Relevé des prix réellement pratiqués à Niamey pour ces quatre familles de machines.
A41: • Disponibilité des pièces d'usure (tamis, courroies, marteaux, vis de presse) : à commander avec la machine.
A42: • Norme électrique de la presse à huile (4 kW) : vérifier la compatibilité 220 V / 380 V avec le réseau du client.
